Metadata-Version: 2.1
Name: odoo-addon-fieldservice_account_analytic
Version: 17.0.1.1.0.2
Requires-Python: >=3.10
Requires-Dist: odoo-addon-fieldservice_account>=17.0dev,<17.1dev
Requires-Dist: odoo>=17.0a,<17.1dev
Summary: Track analytic accounts on Field Service locations and orders
Home-page: https://github.com/OCA/field-service
License: AGPL-3
Author: Open Source Integrators, Odoo Community Association (OCA)
Author-email: support@odoo-community.org
Classifier: Programming Language :: Python
Classifier: Framework :: Odoo
Classifier: Framework :: Odoo :: 17.0
Classifier: License :: OSI Approved :: GNU Affero General Public License v3
Classifier: Development Status :: 4 - Beta
